tclab/__init__.py
tclab/__main__.py
tclab/experiment.py
tclab/gui.py
tclab/historian.py
tclab/labtime.py
tclab/tclab.py
tclab/version.py
tclab-1.0.0.dist-info/LICENSE.txt
tclab-1.0.0.dist-info/METADATA
tclab-1.0.0.dist-info/WHEEL
tclab-1.0.0.dist-info/top_level.txt
tclab-1.0.0.dist-info/RECORD
